pygluelock/__init__.py
pygluelock/__main__.py
pygluelock/constants.py
pygluelock/exceptions.py
pygluelock/glue_lock.py
pygluelock/utils.py
pygluelock-0.3.0.dist-info/licenses/LICENSE
pygluelock-0.3.0.dist-info/METADATA
pygluelock-0.3.0.dist-info/WHEEL
pygluelock-0.3.0.dist-info/entry_points.txt
pygluelock-0.3.0.dist-info/top_level.txt
pygluelock-0.3.0.dist-info/RECORD
