Metadata-Version: 2.4
Name: pygluelock
Version: 0.3.0
Summary: pygluelock is a sync wrapper around glue lock API
Author-email: Adnan Hossain <fadnanhossain@hotmail.com>
Maintainer-email: Adnan Hossain <fadnanhossain@hotmail.com>
License-Expression: MIT
Project-URL: bugs, https://github.com/aniiik/pygluelock/issues
Project-URL: changelog, https://github.com/aniiik/pygluelock/blob/master/changelog.md
Project-URL: homepage, https://github.com/aniiik/pygluelock
Classifier: Development Status :: 3 - Alpha
Classifier: Intended Audience :: Developers
Classifier: Operating System :: OS Independent
Classifier: Programming Language :: Python
Classifier: Programming Language :: Python :: 3
Classifier: Programming Language :: Python :: 3.10
Classifier: Programming Language :: Python :: 3.11
Classifier: Programming Language :: Python :: 3.12
Classifier: Topic :: Software Development :: Libraries :: Python Modules
Requires-Python: >=3.10
License-File: LICENSE
Requires-Dist: aiohttp
Provides-Extra: test
Requires-Dist: pytest; extra == "test"
Requires-Dist: ruff; extra == "test"
Requires-Dist: ipdb; extra == "test"
Dynamic: license-file
